YDBLoader/YDBLoader.py
YDBLoader/YDBType.py
YDBLoader/__init__.py
YDBLoader/BuildingDefine/ComponentType.py
YDBLoader/BuildingDefine/__init__.py
YDBLoader/BuildingDefine/Beam/Beam.py
YDBLoader/BuildingDefine/Beam/__init__.py
YDBLoader/BuildingDefine/Column/Column.py
YDBLoader/BuildingDefine/Column/__init__.py
YDBLoader/BuildingDefine/Geometry/Grid.py
YDBLoader/BuildingDefine/Geometry/Joint.py
YDBLoader/BuildingDefine/Geometry/StandFloor.py
YDBLoader/BuildingDefine/Geometry/__init__.py
YDBLoader/BuildingDefine/GlobalResult/SeismicResult.py
YDBLoader/BuildingDefine/GlobalResult/__init__.py
YDBLoader/BuildingDefine/Section/Section.py
YDBLoader/BuildingDefine/Section/ShapeEnum.py
YDBLoader/BuildingDefine/Section/__init__.py
YDBLoader/BuildingDefine/Slab/Slab.py
YDBLoader/BuildingDefine/Slab/__init__.py
YDBLoader/SQLiteConnector/Connector.py
YDBLoader/SQLiteConnector/RowDataFactory.py
YDBLoader/SQLiteConnector/YDBTableName.py
YDBLoader/SQLiteConnector/__init__.py
yjk_db_load-0.0.10.dist-info/LICENSE
yjk_db_load-0.0.10.dist-info/METADATA
yjk_db_load-0.0.10.dist-info/WHEEL
yjk_db_load-0.0.10.dist-info/top_level.txt
yjk_db_load-0.0.10.dist-info/RECORD
